Workbook
Name Slicer_Region: #N/A
Name Slicer_Years__Invoice_Date: #N/A

Sheet Cover Page
C3: Dashboard Dataset
C7: Get 10% OFF our course using coupon code EMAIL10
C9: Get our Excel for Business and Finance course.
C11: Made by Career Principles Ltd.
C13: Note
C14: All content is copyright material of Career Principles Ltd.
C15: This Excel model may not be reproduced or distributed by any means, including printing, screencapturing, or any other method without the prior permission of the publisher.

Sheet Data
B2: Retailer Dataset
B4: Retailer | C4: Retailer ID | D4: Invoice Date | E4: Region | F4: State | G4: City | H4: Beverage Brand | I4: Price per Unit | J4: Units Sold | K4: Total Sales | L4: Operating Profit | M4: Operating Margin
B5: BevCo | C5: 1185732 | D5: 44562 | E5: Northeast | F5: New York | G5: New York | H5: Coca-Cola | I5: 0.5 | J5: 12000 | K5: 6000 | L5: 3000 | M5: 0.5
B6: BevCo | C6: 1185732 | D6: 44563 | E6: Northeast | F6: New York | G6: New York | H6: Diet Coke | I6: 0.5 | J6: 10000 | K6: 5000 | L6: 1500 | M6: 0.3
B7: BevCo | C7: 1185732 | D7: 44564 | E7: Northeast | F7: New York | G7: New York | H7: Sprite | I7: 0.4 | J7: 10000 | K7: 4000 | L7: 1400 | M7: 0.35
B8: BevCo | C8: 1185732 | D8: 44565 | E8: Northeast | F8: New York | G8: New York | H8: Fanta | I8: 0.45 | J8: 8500 | K8: 3825 | L8: 1338.75 | M8: 0.35
B9: BevCo | C9: 1185732 | D9: 44566 | E9: Northeast | F9: New York | G9: New York | H9: Powerade | I9: 0.6 | J9: 9000 | K9: 5400 | L9: 1620 | M9: 0.3
B10: BevCo | C10: 1185732 | D10: 44567 | E10: Northeast | F10: New York | G10: New York | H10: Dasani Water | I10: 0.5 | J10: 10000 | K10: 5000 | L10: 1250 | M10: 0.25
B11: BevCo | C11: 1185732 | D11: 44568 | E11: Northeast | F11: New York | G11: New York | H11: Coca-Cola | I11: 0.5 | J11: 12500 | K11: 6250 | L11: 3125 | M11: 0.5
B12: BevCo | C12: 1185732 | D12: 44569 | E12: Northeast | F12: New York | G12: New York | H12: Diet Coke | I12: 0.5 | J12: 9000 | K12: 4500 | L12: 1350 | M12: 0.3
B13: BevCo | C13: 1185732 | D13: 44582 | E13: Northeast | F13: New York | G13: New York | H13: Sprite | I13: 0.4 | J13: 9500 | K13: 3800 | L13: 1330 | M13: 0.35
B14: BevCo | C14: 1185732 | D14: 44583 | E14: Northeast | F14: New York | G14: New York | H14: Fanta | I14: 0.45 | J14: 8250 | K14: 3712.5 | L14: 1299.375 | M14: 0.35
B15: BevCo | C15: 1185732 | D15: 44584 | E15: Northeast | F15: New York | G15: New York | H15: Powerade | I15: 0.6 | J15: 9000 | K15: 5400 | L15: 1620 | M15: 0.3
B16: BevCo | C16: 1185732 | D16: 44585 | E16: Northeast | F16: New York | G16: New York | H16: Dasani Water | I16: 0.5 | J16: 10000 | K16: 5000 | L16: 1250 | M16: 0.25
... B9652: BevCo | C9652: 1185732 | D9652: 44979 | E9652: Northeast | F9652: New Hampshire | G9652: Manchester | H9652: Sprite | I9652: 0.29 | J9652: 830 | K9652: 240.7 | L9652: 64.989 | M9652: 0.27

Sheet Analyze
A3: Sum of Total Sales | B3: Sum of Operating Profit | C3: Average of Price per Unit | D3: Sum of Units Sold
A4: 2423732.5 | B4: 901550.51 | C4: 0.506298 | D4: 4623490
A7: Beverage | B7: Year
A8: Brands | B8: 2022 | C8: Grand Total
A9: Coca-Cola | B9: 499102 | C9: 499102
A10: Dasani Water | B10: 469270.7 | C10: 469270.7
A11: Diet Coke | B11: 423758.7 | C11: 423758.7
A12: Fanta | B12: 315489.2 | C12: 315489.2
A13: Powerade | B13: 349533.9 | C13: 349533.9
A14: Sprite | B14: 366578 | C14: 366578
A15: Grand Total | B15: 2423732.5 | C15: 2423732.5
A19: Years (Invoice Date) | B19: Quarters (Invoice Date) | C19: Sum of Total Sales | D19: Average of Operating Margin
A20: 2022 | B20: Qtr1 | C20: 692776.1 | D20: 0.40174684 | E20: =(A20) -> 2022 | F20: =(B20) -> Qtr1 | G20: =(C20) -> 692776.1 | H20: =(D20) -> 0.40174684
B21: Qtr2 | C21: 644203.9 | D21: 0.4 | F21: =(B21) -> Qtr2 | G21: =(C21) -> 644203.9 | H21: =(D21) -> 0.4
B22: Qtr3 | C22: 719170.4 | D22: 0.41026549 | F22: =(B22) -> Qtr3 | G22: =(C22) -> 719170.4 | H22: =(D22) -> 0.41026549
B23: Qtr4 | C23: 367582.1 | D23: 0.40243816 | F23: =(B23) -> Qtr4 | G23: =(C23) -> 367582.1 | H23: =(D23) -> 0.40243816
A24: Grand Total | C24: 2423732.5 | D24: 0.40373272 | E24: =(A24) -> Grand Total | F24: =(B24) -> 0 | G24: =(C24) -> 2423732.5 | H24: =(D24) -> 0.40373272
F25: =(B25) -> 0 | G25: =(C25) -> 0 | H25: =(D25) -> 0
F26: =(B26) -> 0 | G26: =(C26) -> 0 | H26: =(D26) -> 0
F27: =(B27) -> 0 | G27: =(C27) -> 0 | H27: =(D27) -> 0
E28: =(A28) -> 0 | G28: =(C28) -> 0 | H28: =(D28) -> 0
A31: Beverage | B31: Year
A32: Brands | B32: 2022 | C32: Grand Total
A33: Amazon | B33: 276210 | C33: 276210
A34: BevCo | B34: 466788 | C34: 466788
A35: FizzyCo | B35: 161210.1 | C35: 161210.1
A36: Target | B36: 9250.3 | C36: 9250.3
A37: Walmart | B37: 339912.5 | C37: 339912.5
A38: West Soda | B38: 1170361.6 | C38: 1170361.6
A39: Grand Total | B39: 2423732.5 | C39: 2423732.5

Sheet Dashboard
C10: Sales by Beverage Brands | H10: Sales by Retailers
C11: Brand | D11: Sales 2023 | E11: Sales 2023 | F11: Variances | H11: Retailer | I11: Sales 2022 | J11: Sales 2023 | K11: Variances
C12: =Analyze!A9 -> Coca-Cola | D12: =Analyze!B9 -> 499102 | E12: =Analyze!C9 -> 499102 | F12: =E12-D12 -> 0 | H12: =Analyze!A33 -> Amazon | I12: =Analyze!B33 -> 276210 | J12: =Analyze!C33 -> 276210 | K12: =J12-I12 -> 0
C13: =Analyze!A10 -> Dasani Water | D13: =Analyze!B10 -> 469270.7 | E13: =Analyze!C10 -> 469270.7 | F13: =E13-D13 -> 0 | H13: =Analyze!A34 -> BevCo | I13: =Analyze!B34 -> 466788 | J13: =Analyze!C34 -> 466788 | K13: =J13-I13 -> 0
C14: =Analyze!A11 -> Diet Coke | D14: =Analyze!B11 -> 423758.7 | E14: =Analyze!C11 -> 423758.7 | F14: =E14-D14 -> 0 | H14: =Analyze!A35 -> FizzyCo | I14: =Analyze!B35 -> 161210.1 | J14: =Analyze!C35 -> 161210.1 | K14: =J14-I14 -> 0
C15: =Analyze!A12 -> Fanta | D15: =Analyze!B12 -> 315489.2 | E15: =Analyze!C12 -> 315489.2 | F15: =E15-D15 -> 0 | H15: =Analyze!A36 -> Target | I15: =Analyze!B36 -> 9250.3 | J15: =Analyze!C36 -> 9250.3 | K15: =J15-I15 -> 0
C16: =Analyze!A13 -> Powerade | D16: =Analyze!B13 -> 349533.9 | E16: =Analyze!C13 -> 349533.9 | F16: =E16-D16 -> 0 | H16: =Analyze!A37 -> Walmart | I16: =Analyze!B37 -> 339912.5 | J16: =Analyze!C37 -> 339912.5 | K16: =J16-I16 -> 0
C17: =Analyze!A14 -> Sprite | D17: =Analyze!B14 -> 366578 | E17: =Analyze!C14 -> 366578 | F17: =E17-D17 -> 0 | H17: =Analyze!A38 -> West Soda | I17: =Analyze!B38 -> 1170361.6 | J17: =Analyze!C38 -> 1170361.6 | K17: =J17-I17 -> 0
C18: Total | D18: =SUM(D12:D17) -> 2423732.5 | E18: =SUM(E12:E17) -> 2423732.5 | F18: =SUM(F12:F17) -> 0 | H18: Total | I18: =Analyze!B39 -> 2423732.5 | J18: =Analyze!C39 -> 2423732.5 | K18: =J18-I18 -> 0
C20: Sales & Operating Profit Margin by Quarter
